LICENSE
README.md
setup.py
Caroline_presentation.egg-info/PKG-INFO
Caroline_presentation.egg-info/SOURCES.txt
Caroline_presentation.egg-info/dependency_links.txt
Caroline_presentation.egg-info/not-zip-safe
Caroline_presentation.egg-info/requires.txt
Caroline_presentation.egg-info/top_level.txt
caroline/__init__.py
caroline/caroline.py
caroline/example/__init__.py
caroline/example/__main__.py
caroline/example/presentation.html
caroline/example/presentation_audience.html
caroline/example/presentation_code.py
caroline/example/presentation_files/4.png
caroline/example/presentation_files/Bloch_Ry.html
caroline/example/presentation_files/Caroline_Herschel.jpeg
caroline/example/presentation_files/bending-light_en.html
caroline/example/presentation_files/em1.png
caroline/example/presentation_files/em2.png
caroline/example/presentation_files/em3.png
caroline/example/presentation_files/em4.png
caroline/example/presentation_files/em5.png
caroline/example/presentation_files/em6.png
caroline/example/presentation_files/faraday.jpg
caroline/example/presentation_files/feynman.mp4
caroline/example/presentation_files/institution_logo_placeholder.jpg
caroline/example/presentation_files/mirror_a1.png
caroline/example/presentation_files/mirror_a2.png
caroline/example/presentation_files/mirror_a3.png
caroline/example/presentation_files/mirror_a4.png
caroline/example/presentation_files/mirror_q.png
caroline/folder2presentation/__main__.py
caroline/html/index.html
caroline/html/manifest.json
caroline/html/minify.sh
caroline/html/package-lock.json
caroline/html/package.json
caroline/html/postcss.config.js
caroline/html/presentation.html
caroline/html/roundtable.html
caroline/html_dist/icon.ico
caroline/html_dist/icon_192.png
caroline/html_dist/icon_512.png
caroline/html_dist/index.html
caroline/html_dist/index.html.gz
caroline/html_dist/manifest.json
caroline/html_dist/fonts/jetbrains-mono-v6-latin-300.eot
caroline/html_dist/fonts/jetbrains-mono-v6-latin-300.svg
caroline/html_dist/fonts/jetbrains-mono-v6-latin-300.ttf
caroline/html_dist/fonts/jetbrains-mono-v6-latin-300.woff
caroline/html_dist/fonts/jetbrains-mono-v6-latin-300.woff2
caroline/html_dist/fonts/jetbrains-mono-v6-latin-500.eot
caroline/html_dist/fonts/jetbrains-mono-v6-latin-500.svg
