Metadata-Version: 2.1
Name: Caroline-presentation
Version: 0.3.1
Summary: Caroline open-source Python framework for interactive web/HTML-based science presentations
Home-page: https://github.com/nikolasibalic/Caroline
Download-URL: https://github.com/nikolasibalic/Caroline/archive/refs/tags/v0.3.1.tar.gz
Author: Nikola Sibalic
Author-email: nikolasibalic@physics.org
License: BSD3
Keywords: presentation,science presentations,HTML5 + JS presentations,Python-based HTML presentation generator,audience interaction,interactive presentations,interactive figures,collaboration tools,quiz in presentation
Classifier: Programming Language :: Python
Classifier: Programming Language :: Python :: 3
Classifier: Intended Audience :: Science/Research
Classifier: Intended Audience :: Education
Classifier: Topic :: Education
Classifier: Topic :: Education :: Computer Aided Instruction (CAI)
Classifier: Topic :: Communications :: Conferencing
Classifier: Topic :: Multimedia :: Graphics :: Presentation
Classifier: Topic :: Multimedia :: Graphics :: Viewers
Classifier: License :: OSI Approved :: BSD License
Classifier: Development Status :: 4 - Beta
License-File: LICENSE
